libgener.py
libgener-1.0.0.dist-info/METADATA
libgener-1.0.0.dist-info/WHEEL
libgener-1.0.0.dist-info/entry_points.txt
libgener-1.0.0.dist-info/top_level.txt
libgener-1.0.0.dist-info/RECORD
